ams_brief/__init__.py
ams_brief/console.py
ams_brief/cover_page_ams.py
ams_brief/cover_page_project.py
ams_brief/data/employees.json
ams_brief/directory.py
ams_brief/employees.py
ams_brief/functions.py
ams_brief/mv.py
ams_brief-0.1.67.dist-info/entry_points.txt
ams_brief-0.1.67.dist-info/WHEEL
ams_brief-0.1.67.dist-info/METADATA
ams_brief-0.1.67.dist-info/RECORD
