Metadata-Version: 2.1
Name: ams-brief
Version: 0.1.67
Summary: 
Author: Lucas
Author-email: lucas@animotions.be
Requires-Python: >=3.9,<4.0
Classifier: Programming Language :: Python :: 3
Classifier: Programming Language :: Python :: 3.10
Classifier: Programming Language :: Python :: 3.9
Requires-Dist: click (>=8.1.3,<9.0.0)
Requires-Dist: fpdf (>=1.7.2,<2.0.0)
Requires-Dist: imagesize (>=1.3.0,<2.0.0)
Requires-Dist: pick (>=1.2.0,<2.0.0)
